odoo/addons/sale_stock_return_request/README.rst
odoo/addons/sale_stock_return_request/__init__.py
odoo/addons/sale_stock_return_request/__manifest__.py
odoo/addons/sale_stock_return_request/i18n/ca.po
odoo/addons/sale_stock_return_request/i18n/es.po
odoo/addons/sale_stock_return_request/i18n/fr.po
odoo/addons/sale_stock_return_request/i18n/it.po
odoo/addons/sale_stock_return_request/i18n/pt.po
odoo/addons/sale_stock_return_request/i18n/sale_stock_return_request.pot
odoo/addons/sale_stock_return_request/models/__init__.py
odoo/addons/sale_stock_return_request/models/sale_order.py
odoo/addons/sale_stock_return_request/models/stock_return_request.py
odoo/addons/sale_stock_return_request/readme/CONTRIBUTORS.md
odoo/addons/sale_stock_return_request/readme/DESCRIPTION.md
odoo/addons/sale_stock_return_request/readme/USAGE.md
odoo/addons/sale_stock_return_request/static/description/icon.png
odoo/addons/sale_stock_return_request/static/description/index.html
odoo/addons/sale_stock_return_request/tests/__init__.py
odoo/addons/sale_stock_return_request/tests/test_stock_return_request.py
odoo/addons/sale_stock_return_request/views/sale_order_views.xml
odoo/addons/sale_stock_return_request/views/sale_return_request_views.xml
odoo_addon_sale_stock_return_request-18.0.1.0.2.dist-info/METADATA
odoo_addon_sale_stock_return_request-18.0.1.0.2.dist-info/WHEEL
odoo_addon_sale_stock_return_request-18.0.1.0.2.dist-info/top_level.txt
odoo_addon_sale_stock_return_request-18.0.1.0.2.dist-info/RECORD
